{
    "MPGR": 29,
    "Events": [
        644491,
        633485,
        584741
    ],
    "Sets": [
        {
            "id": 42922496,
            "entrant1Id": 8816630,
            "entrant2Id": 8851495,
            "entrant1Name": "KJH",
            "entrant2Name": "Drephen",
            "entrant1Score": 3,
            "entrant2Score": 1,
            "completed": true,
            "winnerId": 8816630,
            "loserId": 8851495,
            "winnerName": "KJH",
            "loserName": "Drephen",
            "bracketName": "Top Bracket",
            "bracketId": 1617769,
            "entrant1Players": [
                {
                    "playerId": 3560,
                    "playerTag": "KJH"
                }
            ],
            "entrant2Players": [
                {
                    "playerId": 6839,
                    "playerTag": "Drephen"
                }
            ]
        },
        {
            "id": 42922495,
            "entrant1Id": 8816630,
            "entrant2Id": 8851495,
            "entrant1Name": "KJH",
            "entrant2Name": "Drephen",
            "entrant1Score": 3,
            "entrant2Score": 0,
            "completed": true,
            "winnerId": 8816630,
            "loserId": 8851495,
            "winnerName": "KJH",
            "loserName": "Drephen",
            "bracketName": "Top Bracket",
            "bracketId": 1617769,
            "entrant1Players": [
                {
                    "playerId": 3560,
                    "playerTag": "KJH"
                }
            ],
            "entrant2Players": [
                {
                    "playerId": 6839,
                    "playerTag": "Drephen"
                }
            ]
        },
        {
            "id": 42922493,
            "entrant1Id": 8816630,
            "entrant2Id": 8874250,
            "entrant1Name": "KJH",
            "entrant2Name": "Free Palestine",
            "entrant1Score": 3,
            "entrant2Score": 1,
            "completed": true,
            "winnerId": 8816630,
            "loserId": 8874250,
            "winnerName": "KJH",
            "loserName": "Free Palestine",
            "bracketName": "Top Bracket",
            "bracketId": 1617769,
            "entrant1Players": [
                {
                    "playerId": 3560,
                    "playerTag": "KJH"
                }
            ],
            "entrant2Players": [
                {
                    "playerId": 55110,
                    "playerTag": "Free Palestine"
                }
            ]
        },
        {
            "id": 42922489,
            "entrant1Id": 8816630,
            "entrant2Id": 8862675,
            "entrant1Name": "KJH",
            "entrant2Name": "Free | Balloon Day",
            "entrant1Score": 3,
            "entrant2Score": 0,
            "completed": true,
            "winnerId": 8816630,
            "loserId": 8862675,
            "winnerName": "KJH",
            "loserName": "Free | Balloon Day",
            "bracketName": "Top Bracket",
            "bracketId": 1617769,
            "entrant1Players": [
                {
                    "playerId": 3560,
                    "playerTag": "KJH"
                }
            ],
            "entrant2Players": [
                {
                    "playerId": 428600,
                    "playerTag": "Balloon Day"
                }
            ]
        },
        {
            "id": 42922481,
            "entrant1Id": 8816630,
            "entrant2Id": 8722817,
            "entrant1Name": "KJH",
            "entrant2Name": "Brazmonkey",
            "entrant1Score": 2,
            "entrant2Score": 0,
            "completed": true,
            "winnerId": 8816630,
            "loserId": 8722817,
            "winnerName": "KJH",
            "loserName": "Brazmonkey",
            "bracketName": "Top Bracket",
            "bracketId": 1617769,
            "entrant1Players": [
                {
                    "playerId": 3560,
                    "playerTag": "KJH"
                }
            ],
            "entrant2Players": [
                {
                    "playerId": 61212,
                    "playerTag": "Brazmonkey"
                }
            ]
        },
        {
            "id": 42914945,
            "entrant1Id": 8816630,
            "entrant2Id": 8869086,
            "entrant1Name": "KJH",
            "entrant2Name": "Jopps",
            "entrant1Score": 2,
            "entrant2Score": 0,
            "completed": true,
            "winnerId": 8816630,
            "loserId": 8869086,
            "winnerName": "KJH",
            "loserName": "Jopps",
            "bracketName": "Round Robin",
            "bracketId": 1617753,
            "entrant1Players": [
                {
                    "playerId": 3560,
                    "playerTag": "KJH"
                }
            ],
            "entrant2Players": [
                {
                    "playerId": 267049,
                    "playerTag": "Jopps"
                }
            ]
        },
        {
            "id": 42914942,
            "entrant1Id": 8816630,
            "entrant2Id": 8794319,
            "entrant1Name": "KJH",
            "entrant2Name": "GMAN",
            "entrant1Score": 2,
            "entrant2Score": 0,
            "completed": true,
            "winnerId": 8816630,
            "loserId": 8794319,
            "winnerName": "KJH",
            "loserName": "GMAN",
            "bracketName": "Round Robin",
            "bracketId": 1617753,
            "entrant1Players": [
                {
                    "playerId": 3560,
                    "playerTag": "KJH"
                }
            ],
            "entrant2Players": [
                {
                    "playerId": 44584,
                    "playerTag": "GMAN"
                }
            ]
        },
        {
            "id": 42914939,
            "entrant1Id": 8816630,
            "entrant2Id": 8722639,
            "entrant1Name": "KJH",
            "entrant2Name": "htcp",
            "entrant1Score": 2,
            "entrant2Score": 0,
            "completed": true,
            "winnerId": 8816630,
            "loserId": 8722639,
            "winnerName": "KJH",
            "loserName": "htcp",
            "bracketName": "Round Robin",
            "bracketId": 1617753,
            "entrant1Players": [
                {
                    "playerId": 3560,
                    "playerTag": "KJH"
                }
            ],
            "entrant2Players": [
                {
                    "playerId": 1348266,
                    "playerTag": "htcp"
                }
            ]
        },
        {
            "id": 42914936,
            "entrant1Id": 8816630,
            "entrant2Id": 8855616,
            "entrant1Name": "KJH",
            "entrant2Name": "Eddie",
            "entrant1Score": 2,
            "entrant2Score": 0,
            "completed": true,
            "winnerId": 8816630,
            "loserId": 8855616,
            "winnerName": "KJH",
            "loserName": "Eddie",
            "bracketName": "Round Robin",
            "bracketId": 1617753,
            "entrant1Players": [
                {
                    "playerId": 3560,
                    "playerTag": "KJH"
                }
            ],
            "entrant2Players": [
                {
                    "playerId": 1219,
                    "playerTag": "Eddie"
                }
            ]
        },
        {
            "id": 42914933,
            "entrant1Id": 8816630,
            "entrant2Id": 8849674,
            "entrant1Name": "KJH",
            "entrant2Name": "Squizz",
            "entrant1Score": 2,
            "entrant2Score": 0,
            "completed": true,
            "winnerId": 8816630,
            "loserId": 8849674,
            "winnerName": "KJH",
            "loserName": "Squizz",
            "bracketName": "Round Robin",
            "bracketId": 1617753,
            "entrant1Players": [
                {
                    "playerId": 3560,
                    "playerTag": "KJH"
                }
            ],
            "entrant2Players": [
                {
                    "playerId": 538412,
                    "playerTag": "Squizz"
                }
            ]
        }
    ],
    "W": [
        "drephen",
        "drephen",
        "free palestine",
        "theswooper"
    ],
    "L": [
        "faceroll",
        "fatgoku",
        "mekk",
        "skerzo"
    ]
}